README.md
setup.py
ferramentas_SO/__init__.py
ferramentas_SO/cliente_UDP.py
ferramentas_SO/compara_hashes.py
ferramentas_SO/gerador_hash.py
ferramentas_SO/gerador_senha.py
ferramentas_SO/ip_verificador.py
ferramentas_SO/ocultador.py
ferramentas_SO/open_browser.py
ferramentas_SO/ping_multiplo.py
ferramentas_SO/ping_simples.py
ferramentas_SO/servidor_UDP.py
ferramentas_SO/veriv_phone.py
ferramentas_SO/web_crawler.py
ferramentas_SO/web_scraping.py
ferramentas_SO/wordlist.py
ferramentas_SO.egg-info/PKG-INFO
ferramentas_SO.egg-info/SOURCES.txt
ferramentas_SO.egg-info/dependency_links.txt
ferramentas_SO.egg-info/requires.txt
ferramentas_SO.egg-info/top_level.txt