Metadata-Version: 2.1
Name: ferramentas-SO
Version: 0.0.1
Summary: ferramentas usadas para redes geralmente
Home-page: https://github.com/beto86/ferramentas_SO_packsge.git
Author: Roberto_Rocha
Author-email: beto.brava@gmail.com
License: UNKNOWN
Platform: UNKNOWN
Requires-Python: >=3.8
